{
  "schemaVersion": 1,
  "id": "client_permission_four",
  "version": "${version}",
  "name": "ClientPermissionFourth",
  "description": "",
  "authors": [],
  "contact": {
    "repo": "https://github.com/malken21/Minecraft_ClientPermissionFourth_Fabric"
  },
  "license": "MIT",
  "icon": "assets/client_permission_four/icon.png",
  "environment": "client",
  "entrypoints": {
    "client": [
      "marumasa.client_permission_four.client.MinecraftClient"
    ],
    "main": [
      "marumasa.client_permission_four.Minecraft"
    ]
  },
  "mixins": [
    "client_permission_four.mixins.json"
  ],
  "depends": {
    "fabricloader": ">=${loader_version}",
    "fabric": "*",
    "minecraft": "${minecraft_version}"
  }
}
